spaczz/__init__.py
spaczz/_search/__init__.py
spaczz/_search/fuzzysearcher.py
spaczz/_search/phrasesearcher.py
spaczz/_search/regexsearcher.py
spaczz/_search/searchutil.py
spaczz/_search/similaritysearcher.py
spaczz/_search/tokensearcher.py
spaczz/customattrs.py
spaczz/customtypes.py
spaczz/exceptions.py
spaczz/matcher/__init__.py
spaczz/matcher/_phrasematcher.py
spaczz/matcher/fuzzymatcher.py
spaczz/matcher/regexmatcher.py
spaczz/matcher/similaritymatcher.py
spaczz/matcher/tokenmatcher.py
spaczz/pipeline/__init__.py
spaczz/pipeline/spaczzruler.py
spaczz/py.typed
spaczz/registry/__init__.py
spaczz/registry/fuzzyfuncs.py
spaczz/registry/repatterns.py
spaczz/registry/reweights.py
spaczz/util.py
spaczz-0.6.1.dist-info/LICENSE
spaczz-0.6.1.dist-info/METADATA
spaczz-0.6.1.dist-info/WHEEL
spaczz-0.6.1.dist-info/entry_points.txt
spaczz-0.6.1.dist-info/RECORD
