Metadata-Version: 2.1
Name: spaczz
Version: 0.6.1
Summary: Adds fuzzy matching and additional regex matching support to spaCy.
Home-page: https://github.com/gandersen101/spaczz
License: MIT
Keywords: fuzzy matching,spacy,nlp
Author: Grant Andersen
Author-email: gandersen.codes@gmail.com
Requires-Python: >=3.7,<4.0
Classifier: License :: OSI Approved :: MIT License
Classifier: Programming Language :: Python :: 3
Classifier: Programming Language :: Python :: 3.7
Classifier: Programming Language :: Python :: 3.8
Classifier: Programming Language :: Python :: 3.9
Classifier: Programming Language :: Python :: 3.10
Classifier: Programming Language :: Python :: 3.11
Classifier: Programming Language :: Python :: 3.12
Requires-Dist: catalogue
Requires-Dist: importlib_metadata ; python_version < "3.8"
Requires-Dist: rapidfuzz (>=1.0.0)
Requires-Dist: regex (>=2020.6.8)
Requires-Dist: spacy (>=3.0,<4.0)
Requires-Dist: srsly
Requires-Dist: typing_extensions ; python_version < "3.8"
Project-URL: Documentation, https://spaczz.readthedocs.io
Project-URL: Repository, https://github.com/gandersen101/spaczz
